odoo/addons/mrp_bom_attribute_match/README.rst
odoo/addons/mrp_bom_attribute_match/__init__.py
odoo/addons/mrp_bom_attribute_match/__manifest__.py
odoo/addons/mrp_bom_attribute_match/i18n/es.po
odoo/addons/mrp_bom_attribute_match/i18n/hr.po
odoo/addons/mrp_bom_attribute_match/i18n/it.po
odoo/addons/mrp_bom_attribute_match/i18n/mrp_bom_attribute_match.pot
odoo/addons/mrp_bom_attribute_match/i18n/pt_BR.po
odoo/addons/mrp_bom_attribute_match/i18n/tr.po
odoo/addons/mrp_bom_attribute_match/models/__init__.py
odoo/addons/mrp_bom_attribute_match/models/mrp_bom.py
odoo/addons/mrp_bom_attribute_match/models/mrp_production.py
odoo/addons/mrp_bom_attribute_match/models/product.py
odoo/addons/mrp_bom_attribute_match/readme/CONTRIBUTORS.md
odoo/addons/mrp_bom_attribute_match/readme/DESCRIPTION.md
odoo/addons/mrp_bom_attribute_match/readme/USAGE.md
odoo/addons/mrp_bom_attribute_match/reports/__init__.py
odoo/addons/mrp_bom_attribute_match/reports/mrp_report_bom_structure.py
odoo/addons/mrp_bom_attribute_match/static/description/icon.png
odoo/addons/mrp_bom_attribute_match/static/description/index.html
odoo/addons/mrp_bom_attribute_match/tests/__init__.py
odoo/addons/mrp_bom_attribute_match/tests/common.py
odoo/addons/mrp_bom_attribute_match/tests/test_mrp_bom_attribute_match.py
odoo/addons/mrp_bom_attribute_match/tests/test_mrp_bom_line.py
odoo/addons/mrp_bom_attribute_match/views/mrp_bom_views.xml
odoo_addon_mrp_bom_attribute_match-18.0.1.0.2.1.dist-info/METADATA
odoo_addon_mrp_bom_attribute_match-18.0.1.0.2.1.dist-info/WHEEL
odoo_addon_mrp_bom_attribute_match-18.0.1.0.2.1.dist-info/top_level.txt
odoo_addon_mrp_bom_attribute_match-18.0.1.0.2.1.dist-info/RECORD
