Metadata-Version: 2.1
Name: odoo-addon-mrp_bom_attribute_match
Version: 18.0.1.0.2.1
Requires-Python: >=3.10
Requires-Dist: odoo==18.0.*
Summary: Dynamic BOM component based on product attribute
Home-page: https://github.com/OCA/manufacture
License: AGPL-3
Author: Ilyas, Ooops, Odoo Community Association (OCA)
Author-email: support@odoo-community.org
Classifier: Programming Language :: Python
Classifier: Framework :: Odoo
Classifier: Framework :: Odoo :: 18.0
Classifier: License :: OSI Approved :: GNU Affero General Public License v3
